{
  "usx": "3.0",
  "code": "EZR",
  "book": "Translation 4 Translators 1",
  "metadata": [
    "ide": "65001 - Unicode (UTF-8)",
    "h": "Ezra",
    "toc1": "Ezra",
    "toc2": "Ezra",
    "toc3": "EZR",
    "mt2": "This book contains the account of some of the people of Judah returning to Judah and rebuilding the temple. We call this book",
    "mt1": "Ezra"
  ],
  "contents": [
    "c": "1",
    "style": "s1",
    "text": "Cyrus let the Jews return to Jerusalem",
    "style": "p",
    "text": "\n    ",
    "v": "1",
    "text": "During the first year that Cyrus ruled ",
    "add": "the",
    "text": "the",
    "text": " Persian ",
    "add": "Empire",
    "text": "Empire",
    "text": ", he did something that fulfilled what Jeremiah had prophesied. Yahweh motivated Cyrus to write this message, and then Cyrus sent this message throughout his empire:",
    "style": "pi1",
    "text": "\n    ",
    "v": "2",
    "text": "\u201CI, King Cyrus, who rule ",
    "add": "the",
    "text": "the",
    "text": " Persian ",
    "add": "Empire",
    "text": "Empire",
    "text": ", declare this: \u0027Yahweh, the God ",
    "add": "who is in/rules",
    "text": "who is in/rules",
    "text": " from heaven, has caused me to become the ruler of all the kingdoms ",
    "add": "that I know about",
    "text": "that I know about",
    "text": " on the earth. And he has appointed me ",
    "add": "to enable his people",
    "text": "to enable his people",
    "text": " to build a temple for him in Jerusalem, in Judah ",
    "add": "land",
    "text": "land",
    "text": ". ",
    "v": "3",
    "text": "All you people who belong to God may go up to Jerusalem to rebuild this temple for Yahweh, the God who lives in Jerusalem, the God ",
    "add": "who is worshiped by you",
    "text": "who is worshiped by you",
    "text": " Israeli people. I desire/hope that your God will be with you ",
    "add": "and help those who go there",
    "text": "and help those who go there",
    "text": ". ",
    "v": "4",
    "text": "Those people who are in places where Israelis are living, whose ancestors were exiled here, should contribute silver and gold to those who go. They should also give them supplies ",
    "add": "that they will need for the journey to Jerusalem",
    "text": "that they will need for the journey to Jerusalem",
    "text": ". They should also give them some livestock, and gifts of money to help build the temple of God in Jerusalem.\u0027\u00A0\u201D",
    "style": "p",
    "text": "\n    ",
    "v": "5",
    "text": "Then God motivated some of the priests and \u25C4Levites/men who did work in the temple\u25BA and some of the leaders of the tribes that were descended from Judah and Benjamin to return to Jerusalem. Those whom God motivated got ready to return to Jerusalem and build the temple for Yahweh there. ",
    "v": "6",
    "text": "All of their neighbors helped them by giving them things made of silver and things made of gold, and supplies for the journey, and livestock. They also gave them other valuable gifts, and also gave them money ",
    "add": "to buy things for building the temple",
    "text": "to buy things for building the temple",
    "text": ". ",
    "v": "7",
    "text": "King Cyrus brought out the valuable things that King Nebuchadnezzar\u2019s ",
    "add": "soldiers",
    "text": "soldiers",
    "text": " had taken from the temple of Yahweh in Jerusalem and put in the temple of Nebuchadnezzar\u2019s gods ",
    "add": "in Babylon",
    "text": "in Babylon",
    "text": ". ",
    "v": "8",
    "text": "Cyrus commanded Mithredath, the treasurer of ",
    "add": "the",
    "text": "the",
    "text": " Persian ",
    "add": "Empire",
    "text": "Empire",
    "text": ", to count all these items and then give them to Sheshbazzar, the leader of ",
    "add": "the group that was going to return to",
    "text": "the group that was going to return to",
    "text": " Judah.",
    "style": "p",
    "text": "\n    ",
    "v": "9",
    "text": "This is a list of the items that Cyrus donated:",
    "style": "pi1",
    "text": "30 large gold dishes",
    "style": "pi1",
    "text": "1,000 large silver dishes",
    "style": "pi1",
    "text": "29 silver \u25C4censers/incense burning pans\u25BA",
    "style": "pi1",
    "text": "\n    ",
    "v": "10",
    "text": "30 gold bowls",
    "style": "pi1",
    "text": "410 silver bowls",
    "style": "pi1",
    "text": "1,000 other items.",
    "style": "p",
    "text": "\n    ",
    "v": "11",
    "text": "All together, there were 5,400 items made of silver or gold, that ",
    "add": "were given to",
    "text": "were given to",
    "text": " Sheshbazzar ",
    "add": "to",
    "text": "to",
    "text": " take with him when he and the others returned to Jerusalem.",
    "c": "2",
    "style": "s1",
    "text": "The list of groups that returned to Judah",
    "style": "p",
    "text": "\n    ",
    "v": "1",
    "text": "King Nebuchadnezzar\u2019s ",
    "add": "soldiers",
    "text": "soldiers",
    "text": " had captured many ",
    "add": "Israeli",
    "text": "Israeli",
    "text": " people and taken them to Babylonia. ",
    "add": "Many years later, ",
    "text": "Many years later, ",
    "text": " some Israeli people returned to Judah. Some returned to Jerusalem, and some returned to ",
    "add": "other places in",
    "text": "other places in",
    "text": " Judah. They went to the towns where their ancestors had lived. This is a list of the groups who returned. ",
    "v": "2",
    "text": "The leaders of those groups were Zerubbabel, Jeshua, Nehemiah, Seraiah, Reelaiah, Mordecai, Bilshan, Mispar, Bigvai, Rehum, and Baanah.",
    "style": "p",
    "text": "There were:",
    "style": "b",
    "style": "p",
    "text": "\n    ",
    "add": "People whose ancestors had lived in these towns in Judah:",
    "text": "People whose ancestors had lived in these towns in Judah:",
    "style": "b",
    "text": "\n    ",
    "text": "\n  ",
    "style": "p",
    "text": "\n    ",
    "v": "36",
    "text": "Priests who returned:",
    "style": "p",
    "text": "The ones from the ",
    "add": "rest of the",
    "text": "rest of the",
    "text": " tribe of Levi who returned were:",
    "style": "b",
    "text": "\n    ",
    "text": "\n  ",
    "style": "p",
    "text": "\n    ",
    "v": "43",
    "text": "The \u25C4temple workers/men who would work in the temple\u25BA who were descendants of these men:",
    "style": "li2",
    "text": "Ziha, Hasupha, Tabbaoth,",
    "style": "li2",
    "text": "\n    ",
    "v": "44",
    "text": "Keros, Siaha, Padon,",
    "style": "li2",
    "text": "\n    ",
    "v": "45",
    "text": "Lebanah, Hagabah, Akkub,",
    "style": "li2",
    "text": "\n    ",
    "v": "46",
    "text": "Hagab, Shalmai, Hanan,",
    "style": "li2",
    "text": "\n    ",
    "v": "47",
    "text": "Giddel, Gahar, Reaiah,",
    "style": "li2",
    "text": "\n    ",
    "v": "48",
    "text": "Rezin, Nekoda, Gazzam,",
    "style": "li2",
    "text": "\n    ",
    "v": "49",
    "text": "Uzza, Paseah, Besai,",
    "style": "li2",
    "text": "\n    ",
    "v": "50",
    "text": "Asnah, Meunim, Nephusim,",
    "style": "li2",
    "text": "\n    ",
    "v": "51",
    "text": "Bakbuk, Hakupha, Harhur,",
    "style": "li2",
    "text": "\n    ",
    "v": "52",
    "text": "Bazluth, Mehida, Harsha,",
    "style": "li2",
    "text": "\n    ",
    "v": "53",
    "text": "Barkos, Sisera, Temah,",
    "style": "li2",
    "text": "\n    ",
    "v": "54",
    "text": "Neziah, and Hatipha.",
    "style": "b",
    "style": "p",
    "text": "\n    ",
    "v": "55",
    "text": "These descendants of ",
    "add": "King",
    "text": "King",
    "text": " Solomon\u2019s servants ",
    "add": "returned",
    "text": "returned",
    "text": ":",
    "style": "b",
    "style": "li2",
    "text": "Sotai, Hassophereth, Peruda,",
    "style": "li2",
    "text": "\n    ",
    "v": "56",
    "text": "Jaalah, Darkon, Giddel,",
    "style": "li2",
    "text": "\n    ",
    "v": "57",
    "text": "Shephatiah, Hattil, Pokereth-Hazzebaim, and Ami.",
    "style": "b",
    "style": "p",
    "text": "\n    ",
    "v": "58",
    "text": "Altogether, there were 392 temple workers and descendants of Solomon\u2019s servants who returned.",
    "style": "b",
    "style": "pi1",
    "text": "\n    ",
    "v": "59",
    "text": "There was another group who returned ",
    "add": "to Judah",
    "text": "to Judah",
    "text": " from Tel-Melah, Tel-Harsha, Kerub, Addan, and Immer ",
    "add": "towns in Babylonia",
    "text": "towns in Babylonia",
    "text": ". But they could not prove that they were descendants of ",
    "add": "people who previously lived in",
    "text": "people who previously lived in",
    "text": " Israel.",
    "style": "b",
    "style": "p",
    "text": "\n    ",
    "v": "60",
    "text": "This group included 652 people who were descendants of Delaiah, Tobiah, and Nekoda.",
    "style": "p",
    "text": "\n    ",
    "v": "61",
    "text": "Hobaiah\u2019s clan, Hakkoz\u2019s clan, and Barzillai\u2019s clan also returned. Barzillai had married a woman who was a descendant of Barzillai from ",
    "add": "the",
    "text": "the",
    "text": " Gilead ",
    "add": "region",
    "text": "region",
    "text": ", and he had taken for himself the name of his father-in-law\u2019s clan.",
    "style": "p",
    "text": "\n    ",
    "v": "62",
    "text": "The people in that group searched in the documents that had the names of the ancestors of all the clans, but these men\u2019s names were not found. So they were not permitted do the work that priests did. ",
    "v": "63",
    "text": "The governor told them that they would need to ask a priest to consult Yahweh by ",
    "add": "\u25C4casting/throwing",
    "text": "\u25C4casting/throwing",
    "text": " the sacred lots/stones ",
    "add": "that had been marked",
    "text": "that had been marked",
    "text": "\u25BA, to determine if those men were truly Israelis. When the priests did that, ",
    "add": "if the stones showed that those men were Israelis",
    "text": "if the stones showed that those men were Israelis",
    "text": ", they would be permitted to eat the shares of the sacrifices that were given to the priests.",
    "style": "b",
    "style": "pi1",
    "text": "\n    ",
    "v": "64",
    "text": "Altogether 42,360 Israeli people who returned to Judah. ",
    "v": "65",
    "text": "There were also 7,337 servants and 200 musicians, both men and women, who returned. ",
    "v": "66",
    "text": "The Israelis brought with them ",
    "add": "from Babylonia",
    "text": "from Babylonia",
    "text": " 736 horses, 245 mules, ",
    "v": "67",
    "text": "435 camels, and 6,720 donkeys.",
    "style": "p",
    "text": "\n    ",
    "v": "68",
    "text": "When they arrived at the temple of Yahweh in Jerusalem, some of the clan leaders gave money ",
    "add": "for the supplies needed ",
    "text": "for the supplies needed ",
    "text": " to rebuild the temple at the place where the temple had been previously. ",
    "v": "69",
    "text": "They all gave as much money as they were able to give. Altogether they gave 61,000 gold coins, \u25C46,250 pounds/3,000 kg.\u25BA of silver, and 100 robes for the priests.",
    "style": "p",
    "text": "\n    ",
    "v": "70",
    "text": "Then the priests, the ",
    "add": "other",
    "text": "other",
    "text": " descendants of Levi, the musicians, the temple guards, and some of the ",
    "add": "other",
    "text": "other",
    "text": " people started to live in the towns and villages ",
    "add": "near Jerusalem",
    "text": "near Jerusalem",
    "text": ". The rest of the people went to the other places in Israel where their ancestors had lived.",
    "c": "3",
    "style": "s1",
    "text": "They rebuilt the altar in Jerusalem",
    "style": "p",
    "text": "\n    ",
    "v": "1",
    "text": "After the Israeli people ",
    "add": "returned to Israel, and",
    "text": "returned to Israel, and",
    "text": " had begun to live in their towns, \u25C4in the autumn of/after the hot season ended in\u25BA that year, they all gathered together in Jerusalem. ",
    "v": "2",
    "text": "Then Jeshua, the son of Jehozadak, and his fellow priests, and Zerubbabel the son of Shealtiel and his friends, all began to rebuild the altar of God, the one whom the Israeli people ",
    "add": "worshiped",
    "text": "worshiped",
    "text": ". They did that in order that they could sacrifice burned offerings on it, according to what the prophet Moses had written in the laws ",
    "add": "that God gave to him",
    "text": "that God gave to him",
    "text": ". ",
    "v": "3-6",
    "text": "Even though they were afraid of the people who were already living in that area, they rebuilt the altar at the same place ",
    "add": "where the previous altar had been",
    "text": "where the previous altar had been",
    "text": ". Before they started to lay the foundation of Yahweh\u2019s temple, ",
    "add": "the priests",
    "text": "the priests",
    "text": " started to burn sacrifices to Yahweh ",
    "add": "on the altar",
    "text": "on the altar",
    "text": ". They offered sacrifices every morning and every evening. Fifteen days after ",
    "add": "they started to offer these sacrifices",
    "text": "they started to offer these sacrifices",
    "text": ", the people celebrated the Festival of ",
    "add": "Living in Temporary",
    "text": "Living in Temporary",
    "text": " Shelters, as ",
    "add": "Moses",
    "text": "Moses",
    "text": " had commanded them to do in the laws ",
    "add": "that God gave to him",
    "text": "that God gave to him",
    "text": ". Each day the priests offered the sacrifices ",
    "add": "that were required",
    "text": "that were required",
    "text": " for that day. In addition, they presented the regular burned offerings and the offerings ",
    "add": "that were required",
    "text": "that were required",
    "text": " for the New Moon Festivals and the other festivals that they celebrated each year to ",
    "add": "honor",
    "text": "honor",
    "text": " Yahweh. They also brought other offerings only because they desired to bring them, ",
    "add": "not because they were required to bring them",
    "text": "not because they were required to bring them",
    "text": ".",
    "style": "s1",
    "text": "They rebuilt the temple",
    "style": "p",
    "text": "\n    ",
    "v": "7",
    "text": "Then the Israelis hired masons and carpenters, and they bought ",
    "add": "logs from",
    "text": "logs from",
    "text": " cedar trees from the people of Tyre and Sidon ",
    "add": "cities",
    "text": "cities",
    "text": ", and they gave those people food and wine and olive oil for the logs. They brought the logs down from ",
    "add": "the mountains in",
    "text": "the mountains in",
    "text": " Lebanon ",
    "add": "to the Mediterranean seacoast and then floated them along the coast of the Sea,",
    "text": "to the Mediterranean seacoast and then floated them along the coast of the Sea,",
    "text": " to Joppa. King Cyrus permitted them to do that. ",
    "add": "Then the logs were brought from Joppa inland up to Jerusalem",
    "text": "Then the logs were brought from Joppa inland up to Jerusalem",
    "text": ".",
    "style": "p",
    "text": "\n    ",
    "v": "8",
    "text": "The Israelis started to rebuild the temple in the \u25C4spring/time before the hot season\u25BA of the second year after they returned to Jerusalem. Zerubbabel and Jeshua and all the people who had returned to Jerusalem worked on the building. All the \u25C4Levites/men who did work in the temple\u25BA supervised this work. ",
    "v": "9",
    "text": "Jeshua and his sons and his other relatives, and Kadmiel and his sons, who were descendants of Hodaviah, also helped to supervise the work. The family of Henadad, who were also all Levites, joined with them in supervising this work.",
    "style": "p",
    "text": "\n    ",
    "v": "10",
    "text": "When the builders finished laying the foundation of the temple, the priests put on their robes and stood in their places, blowing their trumpets. Then the Levites, who were descendants of Asaph, clashed/banged their cymbals to praise Yahweh, just as King David had ",
    "add": "many years previously",
    "text": "many years previously",
    "text": " told ",
    "add": "Asaph and the other musicians",
    "text": "Asaph and the other musicians",
    "text": " to do. ",
    "v": "11",
    "text": "They praised Yahweh and thanked him, and they sang this song about him:",
    "style": "q1",
    "text": "\u201CHe is very good ",
    "add": "to us",
    "text": "to us",
    "text": "!",
    "style": "q1",
    "text": "He faithfully loves us Israeli people, and he will love us forever.\u201D",
    "style": "m",
    "text": "Then all the people shouted loudly, praising Yahweh because they had finished laying the foundation of Yahweh\u2019s temple. ",
    "v": "12",
    "text": "Many of the ",
    "add": "old",
    "text": "old",
    "text": " priests, Levites, and leaders of families remembered ",
    "add": "what",
    "text": "what",
    "text": " the first temple ",
    "add": "was like",
    "text": "was like",
    "text": ", and they cried aloud when they saw the foundation of this temple being laid ",
    "add": "because they knew that the new temple would not be as beautiful as the first temple",
    "text": "because they knew that the new temple would not be as beautiful as the first temple",
    "text": ". But the other people shouted joyfully. ",
    "v": "13",
    "text": "The shouting and the crying was very loud; ",
    "add": "even people",
    "text": "even people",
    "text": " far away could hear it.",
    "c": "4",
    "style": "s1",
    "text": "Their enemies opposed rebuilding the temple",
    "style": "p",
    "text": "\n    ",
    "v": "1",
    "text": "The enemies of the people of ",
    "add": "the tribes of",
    "text": "the tribes of",
    "text": " Judah and Benjamin heard that the ",
    "add": "Israeli",
    "text": "Israeli",
    "text": " people who had returned from Babylonia were rebuilding a temple for Yahweh, the God whom the Israeli people ",
    "add": "worshiped",
    "text": "worshiped",
    "text": ". ",
    "v": "2",
    "text": "So they went to Zerubbabel ",
    "add": "the governor",
    "text": "the governor",
    "text": " and the other leaders, and said ",
    "add": "deceptively",
    "text": "deceptively",
    "text": ", \u201CWe want to help ",
    "add": "you build the temple",
    "text": "you build the temple",
    "text": ", because we worship that same God whom you worship, and we have been offering sacrifices to him since Esarhaddon, the King of Assyria, brought us here.\u201D",
    "style": "p",
    "text": "\n    ",
    "v": "3",
    "text": "But Zerubbabel, Jeshua, and the other ",
    "add": "Israeli",
    "text": "Israeli",
    "text": " leaders replied, \u201CWe will not allow you to help us build a temple for our(exc) God. We will build it \u25C4ourselves/without your help\u25BA for Yahweh, the God whom we Israelis worship, like Cyrus, the King of Persia, told us to do.\u201D",
    "style": "p",
    "text": "\n    ",
    "v": "4",
    "text": "Then the people who had been living in that land ",
    "add": "before the Israelis returned",
    "text": "before the Israelis returned",
    "text": " tried to cause the Jews to become discouraged and become afraid, and to cause them to stop building the temple. ",
    "v": "5",
    "text": "They bribed government officials to oppose what the Israelis were doing ",
    "add": "and prevent them from continuing to work on the temple",
    "text": "and prevent them from continuing to work on the temple",
    "text": ". They did that all during the time that Cyrus was King of Persia. They continued to do it when Darius became the King of Persia.",
    "style": "s1",
    "text": "Opposition to rebuilding Jerusalem",
    "style": "p",
    "text": "\n    ",
    "v": "6",
    "text": "During the first year that ",
    "add": "Darius\u2019 son",
    "text": "Darius\u2019 son",
    "text": " Xerxes was king, the ",
    "add": "enemies of the Jews",
    "text": "enemies of the Jews",
    "text": " wrote a note ",
    "add": "to the king",
    "text": "to the king",
    "text": " saying that the Jews ",
    "add": "were planning to rebel against the government",
    "text": "were planning to rebel against the government",
    "text": ".",
    "style": "p",
    "text": "\n    ",
    "v": "7",
    "text": "Later, when ",
    "add": "Xerxes\u2019 son",
    "text": "Xerxes\u2019 son",
    "text": " Artaxerxes ",
    "add": "became the King of Persia",
    "text": "became the King of Persia",
    "text": ", Bishlam, Mithredath, Tabeel and their colleagues/companions wrote a letter to him. They wrote the letter in the Aramaic language, and it was translated ",
    "add": "into another language that the king knew",
    "text": "into another language that the king knew",
    "text": ".",
    "style": "p",
    "text": "\n    ",
    "v": "8",
    "text": "Rehum, the high commissioner, and Shimshai, the provincial secretary, wrote the letter to King Artaxerxes concerning what was happening in Jerusalem.",
    "style": "mi",
    "text": "\n    ",
    "v": "9",
    "text": "They stated that the letter was from Rehum the high commissioner/governor and Shimshai the provincial secretary and from their associates, the judges, and other government officials, who were from Erech ",
    "add": "city",
    "text": "city",
    "text": ", Babylon ",
    "add": "city",
    "text": "city",
    "text": ", and Susa ",
    "add": "city",
    "text": "city",
    "text": " in Elam ",
    "add": "district",
    "text": "district",
    "text": ". ",
    "v": "10",
    "add": "They also wrote that they represented",
    "text": "They also wrote that they represented",
    "text": " the other people-groups whom ",
    "add": "the army of",
    "text": "the army of",
    "text": " the great and glorious/famous ",
    "add": "King",
    "text": "King",
    "text": " Ashurbanipal had \u25C4deported/forced to move from their homes\u25BA and taken to live in Samaria and in other cities in the province west of the Euphrates ",
    "add": "River",
    "text": "River",
    "text": ".",
    "style": "b",
    "style": "p",
    "text": "\n    ",
    "v": "11",
    "text": "This is what they wrote in the letter:",
    "style": "mi",
    "text": "\u201CTo King Artaxerxes,",
    "style": "mi",
    "text": "From the officials who serve you who live in the province west of the Euphrates ",
    "add": "River.",
    "text": "River.",
    "style": "pi1",
    "text": "\n    ",
    "v": "12",
    "text": "\u201CYour majesty, we want you to know that the Jews who came here from your territories are rebuilding this city, ",
    "add": "Jerusalem",
    "text": "Jerusalem",
    "text": ". These people are wicked and want to rebel against you. Now they are repairing the foundations ",
    "add": "of the walls/buildings",
    "text": "of the walls/buildings",
    "text": " and building the walls ",
    "add": "of the city",
    "text": "of the city",
    "text": ".",
    "style": "pi1",
    "text": "\n    ",
    "v": "13",
    "text": "\u201CIt is important for you to know that if they rebuild the city and finish building the walls, they will stop paying any kind of taxes. As a result, there will be less money in your treasury. ",
    "v": "14",
    "text": "Now, because we are loyal to [IDM] you, and because we do not want you to be humiliated [IDM], we are sending this information to you. ",
    "v": "15",
    "text": "And, we suggest that you order/tell ",
    "add": "your officials",
    "text": "your officials",
    "text": " to search the records that your ancestors made/wrote. ",
    "add": "If you do that",
    "text": "If you do that",
    "text": ", you will find out that the people in this city have always rebelled ",
    "add": "against the government",
    "text": "against the government",
    "text": ". You will also find out that from long ago these people have caused trouble for kings and for rulers of provinces. They have always revolted ",
    "add": "against those who ruled them",
    "text": "against those who ruled them",
    "text": ". That is the reason that this city was destroyed ",
    "add": "by the Babylonian army",
    "text": "by the Babylonian army",
    "text": ". ",
    "v": "16",
    "text": "We want you to know that if they rebuild this city and finish building its walls, you will no longer be able to control/rule ",
    "add": "the people in",
    "text": "the people in",
    "text": " this province west of the Euphrates ",
    "add": "River",
    "text": "River",
    "text": ".\u201D",
    "style": "b",
    "style": "p",
    "text": "\n    ",
    "v": "17",
    "text": "\n    ",
    "add": "After",
    "text": "After",
    "text": " the king ",
    "add": "read this letter, he",
    "text": "read this letter, he",
    "text": " sent this reply to them:",
    "style": "pi1",
    "text": "\u201CTo Rehum, the high commissioner, and Shimshai, the provincial secretary, and their colleagues in Samaria and in other parts of the province that is west of the ",
    "add": "Euphrates",
    "text": "Euphrates",
    "text": " River: I \u25C4send you my greetings/wish that things will go well for you\u25BA. ",
    "v": "18",
    "text": "The letter that you sent to me was translated and read to me. ",
    "v": "19",
    "text": "So then I ordered ",
    "add": "my officials",
    "text": "my officials",
    "text": " to search the records. I have found out that ",
    "add": "it is true that",
    "text": "it is true that",
    "text": " the people of that city have always revolted against their rulers, and that the city is full of people who have rebelled and caused trouble. ",
    "v": "20",
    "text": "Powerful kings have ruled in Jerusalem, and they have also ruled over the whole province west of the ",
    "add": "Euphrates",
    "text": "Euphrates",
    "text": " River. ",
    "add": "The people in that province were",
    "text": "The people in that province were",
    "text": " paying all kinds of taxes to those kings. ",
    "v": "21",
    "text": "So you must command that the people must stop rebuilding the city. Only if I tell them ",
    "add": "that they may rebuild it",
    "text": "that they may rebuild it",
    "text": " will they be allowed to continue. ",
    "v": "22",
    "text": "Do this immediately [LIT], because I do not want those people to do anything to harm the things/area about which I am concerned.\u201D",
    "style": "p",
    "text": "\n    ",
    "v": "23",
    "text": "\n    ",
    "add": "Messengers took",
    "text": "Messengers took",
    "text": " that letter to Rehum and Shimshai and their colleagues and read it to them. Then Rehum and the others went quickly to Jerusalem, and they forced the Jews to stop ",
    "add": "rebuilding the city wall",
    "text": "rebuilding the city wall",
    "text": ".",
    "style": "p",
    "text": "\n    ",
    "v": "24",
    "text": "The result was that the Jews stopped rebuilding the temple. They did not do any more work to rebuild the temple until Darius became the King of Persia.",
    "c": "5",
    "style": "s1",
    "text": "Tattenai\u2019s letter to King Darius",
    "style": "p",
    "text": "\n    ",
    "v": "1",
    "text": "At that time two prophets gave messages from God to the Jews in Jerusalem and ",
    "add": "other cities in",
    "text": "other cities in",
    "text": " Judah. The prophets were Haggai and Zechariah, who was a descendant of Iddo. They spoke those messages representing God, whom the Israelis ",
    "add": "worshiped/belonged to",
    "text": "worshiped/belonged to",
    "text": ", the one who was their true king. ",
    "v": "2",
    "text": "Then Zerubbabel and Shealtiel ",
    "add": "led many other people",
    "text": "led many other people",
    "text": " as they started ",
    "add": "again",
    "text": "again",
    "text": " to rebuild the temple of God in Jerusalem. And God\u2019s prophets ",
    "add": "Haggai and Zechariah",
    "text": "Haggai and Zechariah",
    "text": " were with them and helped them.",
    "style": "p",
    "text": "\n    ",
    "v": "3",
    "text": "Then Tattenai the governor of the province west of the ",
    "add": "Euphrates",
    "text": "Euphrates",
    "text": " River and Shethar-Bozenai his assistant and ",
    "add": "some of",
    "text": "some of",
    "text": " their officials went to Jerusalem and said to the people, \u201CWho has permitted you to rebuild this temple and put furnishings in it?\u201D ",
    "v": "4",
    "text": "They also requested the people to tell them the names of the men who were working ",
    "add": "at the temple",
    "text": "at the temple",
    "text": ". ",
    "add": "But the people refused",
    "text": "But the people refused",
    "text": ". ",
    "v": "5",
    "text": "However, God was taking care of the Jewish leaders, so their enemies were not able to prevent the people from continuing ",
    "add": "to rebuild the temple",
    "text": "to rebuild the temple",
    "text": ". ",
    "add": "They continued to work while their enemies",
    "text": "They continued to work while their enemies",
    "text": " sent a report to King Darius, and asked him ",
    "add": "what he wanted them to do",
    "text": "what he wanted them to do",
    "text": " about it.",
    "style": "p",
    "text": "\n    ",
    "v": "6",
    "text": "So Tattenai and Shethar-Bozenai and their officials sent a report to King Darius. ",
    "v": "7",
    "text": "This is what they wrote:",
    "style": "b",
    "style": "q1",
    "text": "\u201CKing Darius, we hope that things are going well for you!",
    "style": "pi1",
    "text": "\n    ",
    "v": "8",
    "text": "\n    ",
    "add": "\u201CWe want you to know that",
    "text": "\u201CWe want you to know that",
    "text": " we went to Judah Province, where the temple of the great God is being rebuilt. The people are building it with huge stones, and they are putting wooden beams in the walls. The work is being done very carefully, and they are progressing well.",
    "style": "pi1",
    "text": "\n    ",
    "v": "9",
    "text": "\u201CWe asked the Jewish leaders, \u2018Who has permitted you to rebuild this temple and put furnishings in it?\u2019 ",
    "v": "10",
    "text": "And we requested them to tell us the names of their leaders, in order that we could tell you who they were.",
    "style": "pi1",
    "text": "\n    ",
    "v": "11",
    "text": "\u201CBut ",
    "add": "instead of telling us their leaders\u2019 names,",
    "text": "instead of telling us their leaders\u2019 names,",
    "text": " what they said was, \u2018We serve the God ",
    "add": "who created",
    "text": "who created",
    "text": " the heaven and the earth. Many years ago a great king ",
    "add": "who ruled",
    "text": "who ruled",
    "text": " us Israeli people ",
    "add": "told our ancestors to",
    "text": "told our ancestors to",
    "text": " build a temple here, and now we are rebuilding it.",
    "style": "b",
    "style": "pi1",
    "text": "\n    ",
    "v": "12",
    "text": "\u201C\u0027But God, ",
    "add": "who rules",
    "text": "who rules",
    "text": " in heaven, allowed ",
    "add": "the armies of",
    "text": "the armies of",
    "text": " Nebuchadnezzar, King of Babylonia, to destroy that temple, because our ancestors did things that caused God to become very angry. Nebuchadnezzar\u2019s army took ",
    "add": "many of",
    "text": "many of",
    "text": " the ",
    "add": "Israeli",
    "text": "Israeli",
    "text": " people to Babylonia.",
    "style": "pi1",
    "text": "\n    ",
    "v": "13",
    "text": "\u201C\u0027However, during the first year that Cyrus the King of Babylon started to rule, he decreed that the temple of God should be rebuilt. ",
    "v": "14",
    "text": "Cyrus returned ",
    "add": "to the Jewish leaders",
    "text": "to the Jewish leaders",
    "text": " all the gold and silver cups that had been taken from the temple in Jerusalem and which had been put in the temple in Babylon. Those cups were given to a man named Sheshbazzar, whom King Cyrus had appointed to be the governor in Judah.",
    "style": "pi1",
    "text": "\n    ",
    "v": "15",
    "text": "\u201C\u0027The king instructed him to take the cups back to Jerusalem, to the place ",
    "add": "from which they had previously been taken",
    "text": "from which they had previously been taken",
    "text": ". He also decreed that they should rebuild the temple at the place where it had been before. So Cyrus appointed Sheshbazzar to be the governor in Judah. He also sent all those things made of gold and silver, for Sheshbazzar to put in the new temple. ",
    "v": "16",
    "text": "So Sheshbazzar did that. He came here to Jerusalem, and ",
    "add": "supervised the men who",
    "text": "supervised the men who",
    "text": " laid the foundation of the temple. And since that time, the people have been working on the temple, but it is not finished yet.\u2019",
    "style": "b",
    "style": "pi1",
    "text": "\n    ",
    "v": "17",
    "text": "\u201CTherefore, your majesty, please order someone to search in the place in Babylon where the important records are kept, to find out whether ",
    "add": "it is true that",
    "text": "it is true that",
    "text": " King Cyrus decreed that God\u2019s temple should be rebuilt in Jerusalem. Then you can tell us what you want us to do about this matter.\u201D",
    "c": "6",
    "style": "s1",
    "text": "What King Darius commanded",
    "style": "p",
    "text": "\n    ",
    "v": "1",
    "text": "\n    ",
    "add": "Later",
    "text": "Later",
    "text": " Darius ",
    "add": "became the ruler of the Persian Empire. When the enemies of the Israelis forced them to stop rebuilding the temple, the Persian officials sent a message to King Darius. They asked him to",
    "text": "became the ruler of the Persian Empire. When the enemies of the Israelis forced them to stop rebuilding the temple, the Persian officials sent a message to King Darius. They asked him to",
    "text": " search the records in the \u25C4archives/government records\u25BA, in the building where the king stored the important documents, ",
    "add": "to find out whether King Cyrus had authorized that the temple should be rebuilt",
    "text": "to find out whether King Cyrus had authorized that the temple should be rebuilt",
    "text": ". ",
    "v": "2",
    "add": "The king commanded someone to search there, but those documents were not there in Babylon",
    "text": "The king commanded someone to search there, but those documents were not there in Babylon",
    "text": ". They found a scroll at the fort in Ecbatana, in Media province, ",
    "add": "that contained the information that they wanted to know",
    "text": "that contained the information that they wanted to know",
    "text": ".",
    "style": "p",
    "text": "This is what was written on that scroll:",
    "style": "pi1",
    "text": "\n    ",
    "v": "3",
    "text": "\u201CDuring the first year that Cyrus ",
    "add": "ruled the empire",
    "text": "ruled the empire",
    "text": ", he sent out a decree concerning the temple of God which is at Jerusalem. In the decree it was stated that a new temple must be built at the same place that ",
    "add": "the Israeli people previously",
    "text": "the Israeli people previously",
    "text": " had offered sacrifices, where the ",
    "add": "original",
    "text": "original",
    "text": " foundation ",
    "add": "of the first temple",
    "text": "of the first temple",
    "text": " was. The temple must be 90 feet high and 90 feet wide. ",
    "v": "4",
    "text": "The building must be made from large stones. After putting down three layers of stones, a layer of timber must be put on top of them. This work will be paid for by money from my treasury. ",
    "v": "5",
    "text": "Also, the gold and silver utensils that King Nebuchadnezzar took from the temple of God in Jerusalem and brought to Babylon must be taken back to Jerusalem. They must be put in God\u2019s temple just as they were in the previous temple.\u201D",
    "style": "b",
    "style": "p",
    "text": "\n    ",
    "v": "6",
    "text": "After reading this, King Darius sent this message ",
    "add": "to the leaders of the Israeli people\u2019s enemies in Jerusalem",
    "text": "to the leaders of the Israeli people\u2019s enemies in Jerusalem",
    "text": ":",
    "style": "pi1",
    "text": "\u201CThis is a message for Tattenai, the governor of the province west of the ",
    "add": "Euphrates",
    "text": "Euphrates",
    "text": " River, and for ",
    "add": "his assistant",
    "text": "his assistant",
    "text": " Shethar-Bozenai, and for all your colleagues: Stay away from that area! ",
    "v": "7",
    "text": "Do not \u25C4interfere with/hinder\u25BA the work of building the temple of God! The temple must be rebuilt at the same place where the former temple was. And do not hinder the governor of the Jews and the elders of the Jews ",
    "add": "while they are doing this work",
    "text": "while they are doing this work",
    "text": ".",
    "style": "pi1",
    "text": "\n    ",
    "v": "8",
    "text": "\u201CFurthermore, I declare that you must help these leaders of the Jews as they rebuild this temple of God ",
    "add": "by giving them funds for the building work",
    "text": "by giving them funds for the building work",
    "text": ".",
    "style": "pi1",
    "text": "\n    ",
    "v": "9",
    "text": "\u201CThe Jewish priests in Jerusalem need young bulls and rams and lambs to sacrifice as they make burned offerings to the God of heaven. You must give them the animals that they need. Also, you must be certain to give them the wheat, salt, wine, and ",
    "add": "olive",
    "text": "olive",
    "text": " oil that they need each day ",
    "add": "for those sacrifices",
    "text": "for those sacrifices",
    "text": ". ",
    "v": "10",
    "text": "If you do that, the Jewish priests will be able to offer sacrifices that please the God who is in heaven, and they will pray that God will bless me and my sons.",
    "style": "pi1",
    "text": "\n    ",
    "v": "11",
    "text": "\u201CIf anyone disobeys this decree, ",
    "add": "my soldiers",
    "text": "my soldiers",
    "text": " will pull a beam from his house. Then ",
    "add": "after they sharpen one end of the beam,",
    "text": "after they sharpen one end of the beam,",
    "text": " they will lift that man up and impale him on that beam. Then they will ",
    "add": "completely destroy that man\u2019s house until only",
    "text": "completely destroy that man\u2019s house until only",
    "text": " a pile of rubble is left. ",
    "v": "12",
    "text": "God has chosen ",
    "add": "that city of",
    "text": "that city of",
    "text": " Jerusalem as the place where people will honor him [MTY]. What I desire is that he will get rid of any king or any nation that tries to change this decree or tries to destroy that temple in Jerusalem. I, Darius, have made this decree. It must be obeyed quickly and thoroughly.\u201D",
    "style": "s1",
    "text": "They completed and dedicated the temple",
    "style": "p",
    "text": "\n    ",
    "v": "13",
    "text": "Tattenai, the governor of the province, and ",
    "add": "his assistant",
    "text": "his assistant",
    "text": " Shethar-Bozenai and their colleagues ",
    "add": "read the message and",
    "text": "read the message and",
    "text": " immediately obeyed the decree of King Darius. ",
    "v": "14",
    "text": "So the Jewish leaders continued their work ",
    "add": "of rebuilding the temple",
    "text": "of rebuilding the temple",
    "text": ". They were greatly encouraged by the messages that the prophets Haggai and Zechariah preached. The Israelis continued building the temple, just like God had commanded them to do and like King Cyrus had decreed. ",
    "v": "15",
    "text": "They finished building it on March 12, during the sixth year that King Darius ",
    "add": "ruled",
    "text": "ruled",
    "text": ".",
    "style": "p",
    "text": "\n    ",
    "v": "16",
    "text": "Then the priests and the Levites and all the other Israeli people who had returned from Babylon very joyfully dedicated the temple. ",
    "v": "17",
    "text": "During ",
    "add": "the ceremony to",
    "text": "the ceremony to",
    "text": " dedicate the temple, they sacrificed 100 young bulls, 200 rams, and 400 lambs. They also sacrificed twelve male goats as an offering in order that ",
    "add": "God would forgive",
    "text": "God would forgive",
    "text": " the sins of the people of the twelve tribes of Israel. ",
    "v": "18",
    "text": "Then the priests and Levites were divided into groups that would ",
    "add": "take turns to",
    "text": "take turns to",
    "text": " serve at the temple. They did this according to what Moses had written ",
    "add": "many years previously",
    "text": "many years previously",
    "text": " in the laws ",
    "add": "that he wrote",
    "text": "that he wrote",
    "text": ".",
    "style": "s1",
    "text": "They celebrated the Passover Festival",
    "style": "p",
    "text": "\n    ",
    "v": "19",
    "text": "On April 21, the Jews who had returned from Babylon celebrated the Passover Festival. ",
    "v": "20",
    "add": "To qualify themselves for offering the sacrifices",
    "text": "To qualify themselves for offering the sacrifices",
    "text": ", the priests and Levites had already purified themselves by performing certain rituals. Then they slaughtered the lambs for the benefit of all the people who had returned from Babylon, for the other priests, and for themselves. ",
    "v": "21",
    "text": "Those who had returned from Babylon and the other people in that land who had turned away from their immoral practices in order to worship Yahweh, the God of the Israeli people, ate the Passover meal. ",
    "v": "22",
    "text": "They celebrated the Unleavened Bread Festival of ",
    "add": "Eating",
    "text": "Eating",
    "text": " Unleavened Bread for seven days. The Israeli people throughout the land were joyful because Yahweh had changed the attitude of the king of Assyria toward them, and as a result, the king had helped them to rebuild the temple of God, the one whom they ",
    "add": "worshiped",
    "text": "worshiped",
    "text": ".",
    "c": "7",
    "style": "s1",
    "text": "Ezra went to Jerusalem",
    "style": "p",
    "text": "\n    ",
    "v": "1",
    "text": "\n    ",
    "add": "Many/Fifty years",
    "text": "Many/Fifty years",
    "text": " later, while Artaxerxes was the king of Persia, I, Ezra came from Babylon here to Jerusalem. I am the son of Seraiah and the grandson of Azariah, and the great-grandson of Hilkiah. ",
    "v": "2",
    "text": "Hilkiah was the son of Shallum, who was the son of Zadok, who was the son of Ahitub, ",
    "v": "3",
    "text": "who was the son of Amariah, who was the son of Azariah, who was the son of Meraioth, ",
    "v": "4",
    "text": "who was the son of Zerahiah, who was the son of Uzzi, who was the son of Bukki, ",
    "v": "5",
    "text": "who was the son of Abishua, who was the son of Phinehas, who was the son of Eleazar, who was the son of Aaron, the ",
    "add": "first",
    "text": "first",
    "text": " Supreme Priest. ",
    "v": "6",
    "text": "I am a man who knows very well the laws that Moses ",
    "add": "wrote",
    "text": "wrote",
    "text": ". Those were the laws that Yahweh, the God whom we Israeli people \u25C4",
    "add": "worship/belong to",
    "text": "worship/belong to",
    "text": "\u25BA, had given to us Israeli people. When I arrived in Jerusalem, Yahweh my God was kind to me, and as a result the ",
    "add": "people",
    "text": "people",
    "text": " gave me everything that I had requested the king to ",
    "add": "tell them to",
    "text": "tell them to",
    "text": " give to me. ",
    "v": "7",
    "text": "Some of the priests, some ",
    "add": "other",
    "text": "other",
    "text": " descendants of Levi, ",
    "add": "some",
    "text": "some",
    "text": " singers, ",
    "add": "some",
    "text": "some",
    "text": " \u25C4gatekeepers/men who guarded the gates of the temple\u25BA, and ",
    "add": "some",
    "text": "some",
    "text": " men who worked in the temple, and some other ",
    "add": "Israeli",
    "text": "Israeli",
    "text": " people came up with me here to Jerusalem. That was during the seventh year that Artaxerxes was the king ",
    "add": "of Persia",
    "text": "of Persia",
    "text": ".",
    "style": "p",
    "text": "\n    ",
    "v": "8-9",
    "text": "We left Babylon on April 8, which was the first day of the Jewish year. Because God was very kind to us, we arrived ",
    "add": "safely",
    "text": "safely",
    "text": " in Jerusalem on August 4 of that year. ",
    "v": "10",
    "text": "During my entire life, I devoted myself to studying the laws of Yahweh, and how to obey those laws. I had also taught those laws and all their regulations to the Israeli people ",
    "add": "for many years",
    "text": "for many years",
    "text": ".",
    "style": "s1",
    "text": "The letter that Artaxerxes gave to Ezra",
    "style": "p",
    "text": "\n    ",
    "v": "11",
    "text": "King Artaxerxes ",
    "add": "knew that",
    "text": "knew that",
    "text": " I am a priest who knows the Jewish laws very well. ",
    "add": "He knew that for many years",
    "text": "He knew that for many years",
    "text": " I had studied those laws and had taught all the rules and regulations of those laws to the Israeli people. ",
    "add": "So before I left Babylon to come to Jerusalem,",
    "text": "So before I left Babylon to come to Jerusalem,",
    "text": " he wrote a letter, and gave a copy to me. ",
    "add": "This is what he wrote",
    "text": "This is what he wrote",
    "text": ":",
    "style": "p",
    "text": "\n    ",
    "v": "12",
    "text": "\n    ",
    "add": "\u201CThis letter is",
    "text": "\u201CThis letter is",
    "text": " from me, Artaxerxes, the greatest of the kings. ",
    "add": "I am giving it",
    "text": "I am giving it",
    "text": " to Ezra the priest, who has studied very well all the rules and regulations that the God ",
    "add": "who is/rules",
    "text": "who is/rules",
    "text": " in heaven ",
    "add": "gave to the Israeli people",
    "text": "gave to the Israeli people",
    "text": ".",
    "style": "b",
    "style": "pi1",
    "text": "\n    ",
    "v": "13",
    "text": "\u201CEzra, I command that when you return to Jerusalem, any of the Israeli people in my kingdom who want to are allowed to go with you. That includes any priests and ",
    "add": "other",
    "text": "other",
    "text": " descendants of Levi ",
    "add": "who will work in the temple",
    "text": "who will work in the temple",
    "text": " who want to go. ",
    "v": "14",
    "text": "I, along with my seven counselors/advisors, am sending you to Jerusalem, in order that you can determine what is happening there and in ",
    "add": "other towns in",
    "text": "other towns in",
    "text": " Judah. You are taking with you [MTY] a copy of God\u2019s laws; make sure that the people are doing everything that is written in those laws. ",
    "v": "15",
    "add": "We are also saying that",
    "text": "We are also saying that",
    "text": " you should take with you the silver and gold that I and my advisors are wanting to give to you, in order that you will present it to be an offering to the God who ",
    "add": "rules",
    "text": "rules",
    "text": " the Israeli people and who lives in Jerusalem. ",
    "v": "16",
    "text": "You should also take any silver and gold that the people in the entire Babylonia province give to you, and the money that the priests and ",
    "add": "other",
    "text": "other",
    "text": " Israeli people have happily said that they would give to you to be offerings for building the temple of their God in Jerusalem. ",
    "v": "17",
    "text": "With this money, you should buy the bulls, rams, lambs, and the grain and wine that the priests will burn on the altar ",
    "add": "outside",
    "text": "outside",
    "text": " the temple of your God in Jerusalem.",
    "style": "pi1",
    "text": "\n    ",
    "v": "18",
    "text": "\u201CIf there is any silver or gold that remains ",
    "add": "you have bought all those things",
    "text": "you have bought all those things",
    "text": ", you and your companions/colleagues are permitted to use it to ",
    "add": "buy",
    "text": "buy",
    "text": " whatever you desire, but buy only things that ",
    "add": "you know that",
    "text": "you know that",
    "text": " God wants you to buy. ",
    "v": "19",
    "text": "We have given to you some valuable items to be used in the temple of your God. Take them also to Jerusalem. ",
    "v": "20",
    "text": "If you need any other things for the temple, you are permitted to get the money for those things from the building here where my government\u2019s money is kept/stored.",
    "style": "pi1",
    "text": "\n    ",
    "v": "21",
    "text": "\u201CAnd I, King Artaxerxes, command this to all the treasurers in the province west of the ",
    "add": "Euphrates",
    "text": "Euphrates",
    "text": " River: \u0027Give to Ezra, the priest who has studied very well the laws of the God ",
    "add": "who is/rules",
    "text": "who is/rules",
    "text": " in heaven, everything that he requests, and give it to him quickly. ",
    "v": "22",
    "text": "The most that you should give to him is \u25C47,500 pounds/3,400 kg.\u25BA of silver, 500 bushels of wheat, 550 gallons of wine, and 550 gallons of ",
    "add": "olive",
    "text": "olive",
    "text": " oil, but give to him all the salt that they need. ",
    "v": "23",
    "text": "Be sure that you provide whatever their God requires for his temple, because we certainly do not [RHQ] want him to be angry with me or with my descendants who will later be kings. ",
    "v": "24",
    "text": "We are also commanding that none of the priests, descendants of Levi, musicians, temple guards, or other men who work in the temple, will be required to pay any kind of taxes.\u0027",
    "style": "pi1",
    "text": "\n    ",
    "v": "25",
    "text": "\u201CEzra, your God has enabled you to become very wise. Using that wisdom, appoint men in the province west of the ",
    "add": "Euphrates",
    "text": "Euphrates",
    "text": " River who will judge cases involving the people, and men who will judge cases involving the government. You must appoint men who know the laws of your God. All of you must teach God\u2019s laws to others who do not know them. ",
    "v": "26",
    "text": "Everyone who does not obey God\u2019s laws or the laws of my government must be punished severely. Some of them will be executed, some will be put in prison, some will be sent out of the country or have all their property taken away from them.\u201D",
    "style": "s1",
    "text": "Ezra praised Yahweh",
    "style": "p",
    "text": "\n    ",
    "v": "27",
    "text": "\n    ",
    "add": "Because King Artaxerxes was very kind like that, I said",
    "text": "Because King Artaxerxes was very kind like that, I said",
    "text": ", \u201CPraise Yahweh, the God whom our ancestors ",
    "add": "worshiped/belonged to",
    "text": "worshiped/belonged to",
    "text": "! He has caused the king to want to honor the temple of Yahweh in Jerusalem. ",
    "v": "28",
    "text": "Because God was very kind to me, the king and all his advisors and all his powerful officials have also been kind to me. So, because God has helped me, I have become encouraged, and I have ",
    "add": "been able to",
    "text": "been able to",
    "text": " persuade some of the Israeli leaders to go up to Jerusalem with me.\u201D",
    "c": "8",
    "style": "s1",
    "text": "The clans that returned with Ezra to Jerusalem",
    "style": "p",
    "text": "\n    ",
    "v": "1",
    "text": "This is a list of the names of the leaders of the clans who came with me up ",
    "add": "to Jerusalem",
    "text": "to Jerusalem",
    "text": " from Babylonia when Artaxerxes was the king ",
    "add": "of Persia",
    "text": "of Persia",
    "text": ":",
    "style": "b",
    "style": "li1",
    "text": "\n    ",
    "v": "2",
    "text": "Gershom, from the clan descended from ",
    "add": "Aaron\u2019s grandson",
    "text": "Aaron\u2019s grandson",
    "text": " Phinehas",
    "style": "li1",
    "text": "Daniel, from the clan descended from ",
    "add": "Aaron\u2019s son",
    "text": "Aaron\u2019s son",
    "text": " Ithamar",
    "style": "li1",
    "text": "Hattush, the son of Shecaniah, from the clan descended from King David",
    "style": "li1",
    "text": "\n    ",
    "v": "3",
    "text": "Zechariah and 150 ",
    "add": "other",
    "text": "other",
    "text": " men from the clan descended from Parosh",
    "style": "li1",
    "text": "\n    ",
    "v": "4",
    "text": "Eliehoenai the son of Zerahiah and 200 other men from the clan descended from Pahath-Moab",
    "style": "li1",
    "text": "\n    ",
    "v": "5",
    "text": "Shecaniah the son of Jahaziel and 300 other men from the clan descended from Zattu",
    "style": "li1",
    "text": "\n    ",
    "v": "6",
    "text": "Ebed the son of Jonathan and 50 other men from the clan descended from Adin",
    "style": "li1",
    "text": "\n    ",
    "v": "7",
    "text": "Jeshaiah the son of Athaliah and 70 other men from the clan descended from Elam",
    "style": "li1",
    "text": "\n    ",
    "v": "8",
    "text": "Zebadiah the son of Michael and 80 other men from the clan descended from Shephatiah",
    "style": "li1",
    "text": "\n    ",
    "v": "9",
    "text": "Obadiah the son of Jehiel and 218 other men from the clan descended from Joab",
    "style": "li1",
    "text": "\n    ",
    "v": "10",
    "text": "Shelomith the son of Josiphiah and 160 other men from the clan descended from Bani",
    "style": "li1",
    "text": "\n    ",
    "v": "11",
    "text": "Zechariah the son of Bebai and 28 other men from the clan descended from ",
    "add": "another man whose name was",
    "text": "another man whose name was",
    "text": " Bebai",
    "style": "li1",
    "text": "\n    ",
    "v": "12",
    "text": "Johanan the son of Hakkatan and 110 other men from the clan descended from Azgad",
    "style": "li1",
    "text": "\n    ",
    "v": "13",
    "text": "Also Eliphelet, Jeuel, and Shemaiah, who returned ",
    "add": "here",
    "text": "here",
    "text": " later with 60 men from the clan descended from Adonikam",
    "style": "li1",
    "text": "\n    ",
    "v": "14",
    "text": "And Uthai and Zaccur and 70 other men from the clan descended from Bigvai.",
    "style": "s1",
    "text": "Ezra and the others prepared to return to Jerusalem",
    "style": "p",
    "text": "\n    ",
    "v": "15",
    "text": "I gathered all of them together at the canal that goes ",
    "add": "from Babylon",
    "text": "from Babylon",
    "text": " to Ahava ",
    "add": "town",
    "text": "town",
    "text": ". We set up our tents there and stayed there for three days. ",
    "add": "During that time",
    "text": "During that time",
    "text": " I checked the lists of names and found out that there were priests ",
    "add": "going with us",
    "text": "going with us",
    "text": ", but no ",
    "add": "other",
    "text": "other",
    "text": " descendants of Levi ",
    "add": "who could help them in the temple",
    "text": "who could help them in the temple",
    "text": ". ",
    "v": "16",
    "text": "So I summoned Eliezer, Ariel, Shemaiah, two men whose names were Elnathan, and Jarib, Nathan, Zechariah, and Meshullam, who were all leaders ",
    "add": "of the people",
    "text": "of the people",
    "text": ". I also summoned Joiarib and another Elnathan, who were wise. ",
    "v": "17",
    "text": "I sent them all to Iddo, the leader of the descendants of Levi, who was living in Casiphia ",
    "add": "town",
    "text": "town",
    "text": ", to request that he and his relatives and other men who had worked in the temple send to us some men who would ",
    "add": "go/come with us to",
    "text": "go/come with us to",
    "text": " work in God\u2019s new temple ",
    "add": "in Jerusalem",
    "text": "in Jerusalem",
    "text": ".",
    "style": "p",
    "text": "\n    ",
    "v": "18",
    "text": "Because God was kind to us, they brought to us a man named Sherebiah and 18 of his sons and other relatives. Sherebiah was a very wise man, a descendant of Mahli, ",
    "add": "who was a grandson",
    "text": "who was a grandson",
    "text": " of Levi. ",
    "v": "19",
    "text": "They also sent to us Hashabiah, along with Jeshaiah, descendants of ",
    "add": "Levi\u2019s son",
    "text": "Levi\u2019s son",
    "text": " Merari, and 20 of their relatives. ",
    "v": "20",
    "text": "They also sent 220 other men to work in the temple. Those men\u2019s ancestors had been appointed by King David to assist the descendants of Levi ",
    "add": "who helped the priests in the temple",
    "text": "who helped the priests in the temple",
    "text": ". I listed/wrote the names of all those men.",
    "style": "p",
    "text": "\n    ",
    "v": "21",
    "text": "There alongside the Ahava Canal, I told them that we all would \u25C4fast/abstain from eating food\u25BA and pray. I also told them that we should humble ourselves in the presence of our God. We prayed that God would protect us while we traveled, and also protect our children and our possessions/belongings. ",
    "v": "22",
    "text": "Previously we had told the king that our God takes care of all those who truly trust in him, but that he becomes very angry with those who refuse to obey him. So I would have been ashamed if I had asked the king to send soldiers and men riding on horses to protect us from our enemies while we were traveling along the road. ",
    "v": "23",
    "text": "So we \u25C4fasted/abstained from eating food\u25BA and requested God to protect us, and he \u25C4answered our prayers/did what we requested.\u25BA",
    "style": "s1",
    "text": "The gifts for the temple",
    "style": "p",
    "text": "\n    ",
    "v": "24",
    "text": "I chose twelve of the leaders of the priests, Sherebiah and Hashabiah and ten of their relatives. ",
    "v": "25",
    "text": "I appointed them to supervise carrying to Jerusalem the gifts of silver and gold and the other valuable items that the king and his advisors and other officials, and the Israeli people ",
    "add": "who were living in Babylonia",
    "text": "who were living in Babylonia",
    "text": ", had contributed for the temple of our God. ",
    "v": "26",
    "text": "As I gave these various items to those priests, I weighed each of the items. This was the total: 25 tons of silver, 100 items made from silver that altogether weighed 7,500 pounds, \u25C47,500 pounds/3,400 kg.\u25BA of gold, ",
    "v": "27",
    "text": "20 gold bowls that altogether weighed \u25C419 pounds/8.6 kg.\u25BA, and two items made of polished bronze that were as valuable as ones made of gold.",
    "style": "p",
    "text": "\n    ",
    "v": "28",
    "text": "I said to those priests, \u201CYou belong to Yahweh, the God whom our ancestors \u25C4worshiped/also belonged to\u25BA, and these valuable things also belong to him. The people themselves gave these things to be offerings to Yahweh \u25C4voluntarily/because they wanted to\u25BA. ",
    "v": "29",
    "text": "So guard them carefully, and ",
    "add": "when we arrive",
    "text": "when we arrive",
    "text": " in Jerusalem, weigh them in the presence of the priests, the descendants of Levi ",
    "add": "who will help the priests",
    "text": "who will help the priests",
    "text": ", and the other Israeli leaders there. They will then put them in the storerooms in the new temple.\u201D ",
    "v": "30",
    "text": "So the priests and ",
    "add": "other",
    "text": "other",
    "text": " descendants of Levi took from me all the gifts of silver and gold and the other valuable items, in order to carry them to the temple in Jerusalem.",
    "style": "s1",
    "text": "They returned to Jerusalem",
    "style": "p",
    "text": "\n    ",
    "v": "31",
    "text": "On April 19, we left the Ahava Canal and started to travel to Jerusalem. Our God took care of us, and while we traveled, he prevented our enemies and bandits from \u25C4ambushing us/suddenly attacking us\u25BA. ",
    "v": "32",
    "text": "After we arrived in Jerusalem, we rested for three days. ",
    "v": "33",
    "text": "Then on the fourth/next day we went to the temple. There the silver and gold and the other items were weighed and given to the priest Meremoth, the son of Uriah. Eleazar the son of Phinehas and two descendants of Levi, Jozabad the son of Jeshua and Noadiah the son of Binnui, were with him.",
    "style": "p",
    "text": "\n    ",
    "v": "34",
    "text": "They counted everything, and wrote down how much they weighed, and wrote ",
    "add": "a description of",
    "text": "a description of",
    "text": " each item.",
    "style": "p",
    "text": "\n    ",
    "v": "35",
    "text": "We who had returned from Babylonia offered to God sacrifices on the altar. We offered twelve bulls for all us Israeli people. We also offered 96 rams and 27 lambs. We also sacrificed twelve goats ",
    "add": "to atone",
    "text": "to atone",
    "text": " for the sins that all the people had committed. These were all completely burned on the altar. ",
    "v": "36",
    "text": "Some of us who returned ",
    "add": "from Babylonia",
    "text": "from Babylonia",
    "text": " took to the governors and other officials of the province west of the ",
    "add": "Euphrates",
    "text": "Euphrates",
    "text": " River the letter that the king had given to us. ",
    "add": "After they read the letter,",
    "text": "After they read the letter,",
    "text": " they did all ",
    "add": "that they were able to do",
    "text": "that they were able to do",
    "text": " for us Israeli people and for the temple of God.",
    "c": "9",
    "style": "s1",
    "text": "Ezra prayed about the Israeli people marrying foreign wives",
    "style": "p",
    "text": "\n    ",
    "v": "1",
    "text": "Some time later, the Jewish leaders came to me and said, \u201CMany Israelis, and even some priests and ",
    "add": "other men who are",
    "text": "other men who are",
    "text": " descendants of Levi ",
    "add": "who work in the temple",
    "text": "who work in the temple",
    "text": ", have not kept themselves from ",
    "add": "doing what",
    "text": "doing what",
    "text": " the other people who are living in this land ",
    "add": "do",
    "text": "do",
    "text": ". They are practicing the detestable things that the Canaan, Heth, Periz, Jebus, Ammon, and Amor people-groups, and the people from Moab and Egypt do. ",
    "v": "2",
    "add": "Specifically, some",
    "text": "Specifically, some",
    "text": " Israeli men have married women who are not Israelis, and they have allowed their sons to do the same thing. So we, God\u2019s sacred people, have become \u25C4contaminated/polluted in God\u2019s sight\u25BA. And some of our leaders and officials have been the first/worst ones to do this.\u201D",
    "style": "p",
    "text": "\n    ",
    "v": "3",
    "text": "When I heard that, ",
    "add": "I became very angry, with the result that",
    "text": "I became very angry, with the result that",
    "text": " I tore my clothes and tore some hair from my head and from my beard. Then I sat down, very shocked/dismayed. ",
    "add": "The Israelis knew that God had warned us that he would punish us if we disobeyed",
    "text": "The Israelis knew that God had warned us that he would punish us if we disobeyed",
    "text": " what he had said to us ",
    "add": "about marrying women who are not Israelis",
    "text": "about marrying women who are not Israelis",
    "text": ". ",
    "v": "4",
    "add": "So",
    "text": "So",
    "text": " many of the Israelis trembled/were afraid when they heard that some of those who had returned from Babylonia had sinned by disobeying the God of us Israelis like that. They came and sat with me until it was time to offer the evening sacrifices ",
    "add": "of grain",
    "text": "of grain",
    "text": ".",
    "style": "p",
    "text": "\n    ",
    "v": "5",
    "text": "When it was time to offer those sacrifices, I was still sitting there, wearing those torn clothes and mourning/sad. I stood up, and then I quickly prostrated myself on the ground. I lifted up my hands to Yahweh, my God, ",
    "v": "6",
    "text": "and this is what I prayed:",
    "style": "pi1",
    "text": "\u201CYahweh my God, I am very ashamed to raise my head in front of you. The sins that we Israelis have committed ",
    "add": "are very great; it is as though they",
    "text": "are very great; it is as though they",
    "text": " have risen up higher than our heads, and our guilt ",
    "add": "for committing those sins, it is as though it",
    "text": "for committing those sins, it is as though it",
    "text": " rises up to the heavens. ",
    "v": "7",
    "text": "Since the time that our ancestors lived until now, we have been very guilty. That is the reason that we and our kings and our priests have been defeated by ",
    "add": "the armies of",
    "text": "the armies of",
    "text": " the kings of other lands. They killed ",
    "add": "some of our people",
    "text": "some of our people",
    "text": ", they captured ",
    "add": "some",
    "text": "some",
    "text": ", they robbed ",
    "add": "some",
    "text": "some",
    "text": ", and they ",
    "add": "caused them all to be",
    "text": "caused them all to be",
    "text": " disgraced, just like we are today.",
    "style": "pi1",
    "text": "\n    ",
    "v": "8",
    "text": "\u201CBut now, Yahweh God, you have been very kind to us. You have allowed some of us to \u25C4survive/continue to live\u25BA. You have revived our spirits [IDM] and allowed us to escape from being slaves ",
    "add": "in Babylonia",
    "text": "in Babylonia",
    "text": " and to return safely [IDM] to live in this sacred place. ",
    "v": "9",
    "text": "We were slaves, but you did not abandon us. Instead, because you faithfully love us, you caused the kings of Persia to be very kind to us. You have allowed us to continue to live and to rebuild your temple which had been completely destroyed. You have allowed us to start to live safely here in Jerusalem and in ",
    "add": "other towns in",
    "text": "other towns in",
    "text": " Judah.",
    "style": "pi1",
    "text": "\n    ",
    "v": "10",
    "text": "\u201COur God, what more can we say now [RHQ]? In spite of all that ",
    "add": "you have done for us",
    "text": "you have done for us",
    "text": ", we have disobeyed your commands. ",
    "v": "11",
    "text": "They are commands that you gave to your servants, the prophets, to tell to us. They said that the land that we would occupy was polluted because of the detestable/disgusting things that were done by the people who lived there. They said that in the land there were people from one end to the other who did immoral/shameful things. ",
    "v": "12",
    "text": "They said, \u2018Do not allow your daughters to marry their sons! Do not allow your sons to marry their daughters! Do not even try to cause things to go well for those people-groups! If you obey these instructions, your nation will be strong, and you will enjoy the good crops that grow on the land, and the land will belong to your descendants forever.\u2019",
    "style": "pi1",
    "text": "\n    ",
    "v": "13",
    "text": "\u201CYou punished us because we were very guilty for having done wicked things. But you have not punished us as much as we deserve to be punished. ",
    "add": "I say this because",
    "text": "I say this because",
    "text": " you, our God, have allowed some of us to survive. ",
    "v": "14",
    "text": "However, some of us are again disobeying your commands, and we are marrying women who do those detestable things. If we continue to do that, surely you will get rid of all of us [RHQ], with the result that none of us will remain alive. ",
    "v": "15",
    "text": "Yahweh, the God whom we Israelis ",
    "add": "worship/belong to",
    "text": "worship/belong to",
    "text": ", you are fair/just. We are guilty. We are only a few people who have escaped ",
    "add": "from Babylonia",
    "text": "from Babylonia",
    "text": ", but we pray to you, even though we do not deserve to stand in your presence.\u201D",
    "c": "10",
    "style": "s1",
    "text": "The men agreed to divorce their foreign wives",
    "style": "p",
    "text": "\n    ",
    "v": "1",
    "text": "While I was kneeling down in front of the temple and praying and crying, I was confessing ",
    "add": "the sins that the Israeli people had committed",
    "text": "the sins that the Israeli people had committed",
    "text": ". Many people, men and women and children, gathered around me and also cried very much. ",
    "v": "2",
    "text": "Then Shecaniah, the son of Jehiel from the clan of Elam, said this to me: \u201CWe have disobeyed God. ",
    "add": "Some of",
    "text": "Some of",
    "text": " us have married women who are not Israelis. But we can still confidently expect ",
    "add": "Yahweh to be merciful to",
    "text": "Yahweh to be merciful to",
    "text": " us Israeli people. ",
    "v": "3",
    "text": "We will do what you, and the others who have an awesome respect for what our God has commanded, tell us to do. We will do what God told us in his laws. We will make an agreement with our God, saying that we will divorce our wives who are not Israelis, and we will send them away with their children. ",
    "v": "4",
    "text": "\u25C4It is your responsibility to/Because you are our leader, you must\u25BA ",
    "add": "tell us what to do",
    "text": "tell us what to do",
    "text": ". So get up, and be courageous, and do ",
    "add": "what is necessary",
    "text": "what is necessary",
    "text": ". We will \u25C4support you/tell people to do what you say\u25BA.\u201D",
    "style": "p",
    "text": "\n    ",
    "v": "5",
    "text": "So I stood up and demanded that the leaders of the priests, the ",
    "add": "other",
    "text": "other",
    "text": " descendants of Levi, and all ",
    "add": "the other",
    "text": "the other",
    "text": " Israeli people solemnly declare that they would do what Shecaniah said that they should do. So they all solemnly promised to do that. ",
    "v": "6",
    "text": "Then I went away from the front of the temple and went to the room where Jehohanan lived. I stayed there that night, but I did not eat or drink anything. I was still sad because some of the Israelis who had returned ",
    "add": "from Babylonia",
    "text": "from Babylonia",
    "text": " had not faithfully obeyed ",
    "add": "God\u2019s laws",
    "text": "God\u2019s laws",
    "text": ".",
    "style": "p",
    "text": "\n    ",
    "v": "7",
    "text": "Then we sent a message to all ",
    "add": "the people in",
    "text": "the people in",
    "text": " Jerusalem and ",
    "add": "in other towns in",
    "text": "in other towns in",
    "text": " Judah, saying that all those who had returned ",
    "add": "from Babylonia",
    "text": "from Babylonia",
    "text": " should come to Jerusalem immediately. ",
    "v": "8",
    "text": "We said that if any of them did not arrive within three days, the leaders of the people would order that all the property of those people would be taken from them, and that they would no longer be considered to belong to the Israeli people; ",
    "add": "they would be considered to be foreigners",
    "text": "they would be considered to be foreigners",
    "text": ".",
    "style": "p",
    "text": "\n    ",
    "v": "9",
    "text": "So within three days, on December 19, all the people of the tribes of Judah and Benjamin gathered in Jerusalem. They were there, sitting in the courtyard in front of the temple. They were trembling because it was raining hard and because they were worried ",
    "add": "that they would be punished for what they had done",
    "text": "that they would be punished for what they had done",
    "text": ". ",
    "v": "10",
    "text": "Then I stood up and said to them, \u201C",
    "add": "Some of",
    "text": "Some of",
    "text": " you men have committed a very bad sin. You have married women who are not Israelis. By doing that, you have made us Israeli people more guilty ",
    "add": "than we were before",
    "text": "than we were before",
    "text": ". ",
    "v": "11",
    "text": "So now you must confess to Yahweh, the God whom your ancestors ",
    "add": "worshiped/belonged to",
    "text": "worshiped/belonged to",
    "text": ", the sin which you have committed, and you must do what he wants. Separate yourselves from the people of other nations and from the women from those nations whom you have married.\u201D",
    "style": "p",
    "text": "\n    ",
    "v": "12",
    "text": "The whole group answered, shouting loudly, \u201CYes, what you have said is right! We will do what you have said.\u201D ",
    "v": "13",
    "text": "But then ",
    "add": "one of",
    "text": "one of",
    "text": " them said, \u201CBut we are a very large group, and it is raining hard. Also, there are many of us who have committed this bad sin. This is something that we cannot \u25C4take care of/handle\u25BA in one or two days, and we cannot stand here in this rain. ",
    "v": "14",
    "text": "So allow our leaders to decide for all of us what we should do. Tell everyone who has married a woman who is not Israeli to come at a time that you decide. They should come with the elders and judges from each city. If we do that, our God will stop being angry with us ",
    "add": "because of what we have done",
    "text": "because of what we have done",
    "text": ".\u201D",
    "style": "p",
    "text": "\n    ",
    "v": "15",
    "text": "Jonathan the son of Asahel, Jahzeiah the son of Tikvah, Meshullam, and Shabbethai, a descendant of Levi, were the only ones who objected to this.",
    "style": "p",
    "text": "\n    ",
    "v": "16",
    "text": "All the others who had returned from Babylonia said that they would do it. So I chose leaders of each of the clans, and I wrote down their names. On December 29, these men came and sat down to investigate the matter. ",
    "v": "17",
    "text": "By March 27 of the next year they finished determining which men had married women who were not Israelis.",
    "style": "s1",
    "text": "The men who had married foreign wives",
    "style": "li1",
    "text": "\n    ",
    "v": "18",
    "text": "This is a list of the names of the priests who had married non-Israeli women, and the clans to which they belonged. From the clan of Jeshua and his brothers, who were sons of Jehozadak, there were Maaseiah, Eliezer, Jarib, and Gedaliah. ",
    "v": "19",
    "text": "They solemnly promised to divorce their wives, and they each sacrificed a ram to be an offering ",
    "add": "to atone",
    "text": "to atone",
    "text": " for their sins.",
    "style": "li1",
    "text": "\n    ",
    "v": "20",
    "text": "From the clan of Immer there were Hanani and Zebadiah.",
    "style": "li1",
    "text": "\n    ",
    "v": "21",
    "text": "From the clan of Harim there were Maaseiah, Elijah, Shemaiah, Jehiel, and Uzziah.",
    "style": "li1",
    "text": "\n    ",
    "v": "22",
    "text": "From the clan of Pashhur there were Elioenai, Maaseiah, Ishmael, Nethanel, Jozabad, and Elasah.",
    "style": "li1",
    "text": "\n    ",
    "v": "23",
    "text": "The ",
    "add": "other",
    "text": "other",
    "text": " descendants of Levi ",
    "add": "who had married non-Israeli women",
    "text": "who had married non-Israeli women",
    "text": " were Jozabad, Shimei, Kelaiah (whose other name was Kelita), Pethahiah, Judah, and Eliezer.",
    "style": "li1",
    "text": "\n    ",
    "v": "24",
    "text": "There was Eliashib the musician.",
    "style": "li2",
    "text": "From the temple guards there were Shallum, Telem, and Uri.",
    "style": "b",
    "style": "li1",
    "text": "\n    ",
    "v": "25",
    "text": "This is a list of the names of the other Israelis who had married foreign wives:",
    "style": "li1",
    "text": "From the clan of Parosh there were Ramiah, Izziah, Malchijah, Mijamin, Eleazar, Hashabiah, and Benaiah.",
    "style": "li1",
    "text": "\n    ",
    "v": "26",
    "text": "From the clan of Elam there were Mattaniah, Zechariah, Jehiel, Abdi, Jeremoth, and Elijah.",
    "style": "li1",
    "text": "\n    ",
    "v": "27",
    "text": "From the clan of Zattu there were Elioenai, Eliashib, Mattaniah, Jeremoth, Zabad, and Aziza.",
    "style": "li2",
    "text": "\n    ",
    "v": "28",
    "text": "From the clan of Bebai there were Jehohanan, Hananiah, Zabbai, and Athlai.",
    "style": "li1",
    "text": "\n    ",
    "v": "29",
    "text": "From the clan of Bani there were Meshullam, Malluch,, Adaiah, Jashub, Sheal, and Jeremoth.",
    "style": "li1",
    "text": "\n    ",
    "v": "30",
    "text": "From the clan of Pahath-Moab there were Adna, Kelal, Benaiah, Maaseiah, Mattaniah, Bezalel, Binnui, and Manasseh.",
    "style": "li1",
    "text": "\n    ",
    "v": "31",
    "text": "From the clan of Harim there were Eliezer, Ishijah, Malkijah, Shemaiah, Shimeon, ",
    "v": "32",
    "text": "Benjamin, Malluch, and Shemariah.",
    "style": "li1",
    "text": "\n    ",
    "v": "33",
    "text": "From the clan of Hashum there were Mattenai, Mattattah, Zabad, Eliphelet, Jeremai, Manasseh, and Shimei.",
    "style": "li1",
    "text": "\n    ",
    "v": "34",
    "text": "From the clan of Bigvai there were Maadai, Amram, Uel, ",
    "v": "35",
    "text": "Benaiah, Bedeiah, Keluhi, ",
    "v": "36",
    "text": "Vaniah, Meremoth, Eliashib, ",
    "v": "37",
    "text": "Mattaniah, Mattenai, and Jaasu.",
    "style": "li1",
    "text": "\n    ",
    "v": "38",
    "text": "From the clan of Binnui there were Shimei,",
    "style": "li2",
    "text": "\n    ",
    "v": "39",
    "text": "Shelemiah, Nathan, Adaiah, ",
    "v": "40",
    "text": "Macnadebai, Shashai, Sharai, ",
    "v": "41",
    "text": "Azarel, Shelemiah, Shemariah, ",
    "v": "42",
    "text": "Shallum, Amariah, and Joseph.",
    "style": "li1",
    "text": "\n    ",
    "v": "43",
    "text": "From the clan of Nebo there were Jeiel, Mattithiah, Zabad, Zebina, Jaddai, Joel, and Benaiah.",
    "style": "b",
    "style": "p",
    "text": "\n    ",
    "v": "44",
    "text": "Each of those men had married a woman who was not an Israeli. ",
    "add": "But immediately",
    "text": "But immediately",
    "text": " they divorced those women and sent them and their children away."
  ]
}